CHANGELOG.md
LICENSE
MANIFEST.in
README.md
requirements.txt
setup.py
skclust/__init__.py
skclust/graph.py
skclust/hierarchical.py
skclust/neighbors.py