Metadata-Version: 2.4
Name: skclust
Version: 2026.1.24
Summary: A comprehensive clustering toolkit with advanced tree cutting and visualization
Home-page: https://github.com/jolespin/skclust
Author: Josh L. Espinoza
Author-email: jol.espinoz@gmail.com
License: MIT
Project-URL: Bug Reports, https://github.com/jolespin/skclust/issues
Project-URL: Source, https://github.com/jolespin/skclust
Keywords: clustering hierarchical-clustering dendrogram tree-cutting machine-learning data-analysis bioinformatics network-analysis visualization scikit-learn
Classifier: Development Status :: 4 - Beta
Classifier: Intended Audience :: Science/Research
Classifier: Intended Audience :: Developers
Classifier: License :: OSI Approved :: MIT License
Classifier: Programming Language :: Python :: 3
Classifier: Programming Language :: Python :: 3.8
Classifier: Programming Language :: Python :: 3.9
Classifier: Programming Language :: Python :: 3.10
Classifier: Programming Language :: Python :: 3.11
Classifier: Programming Language :: Python :: 3.12
Classifier: Topic :: Scientific/Engineering
Classifier: Topic :: Scientific/Engineering :: Bio-Informatics
Classifier: Topic :: Scientific/Engineering :: Information Analysis
Classifier: Topic :: Software Development :: Libraries :: Python Modules
Classifier: Operating System :: OS Independent
Requires-Python: >=3.8
License-File: LICENSE
Requires-Dist: numpy<2.0.0,>=1.19.0
Requires-Dist: pandas>=1.3.0
Requires-Dist: scipy>=1.7.0
Requires-Dist: scikit-learn>=1.0.0
Requires-Dist: python-igraph
Requires-Dist: loguru
Provides-Extra: fast
Requires-Dist: fastcluster>=1.2.0; extra == "fast"
Provides-Extra: tree
Requires-Dist: scikit-bio>=0.5.6; extra == "tree"
Provides-Extra: dynamic
Requires-Dist: dynamicTreeCut>=0.1.0; extra == "dynamic"
Provides-Extra: network
Requires-Dist: ensemble-networkx>=0.1.0; extra == "network"
Provides-Extra: all
Requires-Dist: fastcluster>=1.2.0; extra == "all"
Requires-Dist: scikit-bio>=0.5.6; extra == "all"
Requires-Dist: dynamicTreeCut>=0.1.0; extra == "all"
Requires-Dist: ensemble-networkx>=0.1.0; extra == "all"
Dynamic: author
Dynamic: author-email
Dynamic: classifier
Dynamic: description
Dynamic: description-content-type
Dynamic: home-page
Dynamic: keywords
Dynamic: license
Dynamic: license-file
Dynamic: project-url
Dynamic: provides-extra
Dynamic: requires-dist
Dynamic: requires-python
Dynamic: summary
